odoo/addons/printer_zpl2/README.rst
odoo/addons/printer_zpl2/__init__.py
odoo/addons/printer_zpl2/__manifest__.py
odoo/addons/printer_zpl2/i18n/am.po
odoo/addons/printer_zpl2/i18n/bg.po
odoo/addons/printer_zpl2/i18n/ca.po
odoo/addons/printer_zpl2/i18n/de.po
odoo/addons/printer_zpl2/i18n/el_GR.po
odoo/addons/printer_zpl2/i18n/es.po
odoo/addons/printer_zpl2/i18n/es_AR.po
odoo/addons/printer_zpl2/i18n/es_ES.po
odoo/addons/printer_zpl2/i18n/fi.po
odoo/addons/printer_zpl2/i18n/fr.po
odoo/addons/printer_zpl2/i18n/gl.po
odoo/addons/printer_zpl2/i18n/hr.po
odoo/addons/printer_zpl2/i18n/hr_HR.po
odoo/addons/printer_zpl2/i18n/it.po
odoo/addons/printer_zpl2/i18n/nl.po
odoo/addons/printer_zpl2/i18n/nl_NL.po
odoo/addons/printer_zpl2/i18n/printer_zpl2.pot
odoo/addons/printer_zpl2/i18n/pt.po
odoo/addons/printer_zpl2/i18n/pt_BR.po
odoo/addons/printer_zpl2/i18n/pt_PT.po
odoo/addons/printer_zpl2/i18n/sl.po
odoo/addons/printer_zpl2/i18n/tr.po
odoo/addons/printer_zpl2/i18n/zh_CN.po
odoo/addons/printer_zpl2/models/__init__.py
odoo/addons/printer_zpl2/models/printing_label_zpl2.py
odoo/addons/printer_zpl2/models/printing_label_zpl2_component.py
odoo/addons/printer_zpl2/models/zpl2.py
odoo/addons/printer_zpl2/readme/CONFIGURE.rst
odoo/addons/printer_zpl2/readme/CONTRIBUTORS.rst
odoo/addons/printer_zpl2/readme/DESCRIPTION.rst
odoo/addons/printer_zpl2/readme/HISTORY.rst
odoo/addons/printer_zpl2/readme/INSTALL.rst
odoo/addons/printer_zpl2/readme/USAGE.rst
odoo/addons/printer_zpl2/security/ir.model.access.csv
odoo/addons/printer_zpl2/static/description/icon.png
odoo/addons/printer_zpl2/static/description/index.html
odoo/addons/printer_zpl2/tests/__init__.py
odoo/addons/printer_zpl2/tests/test_generate_action.py
odoo/addons/printer_zpl2/tests/test_printing_label_zpl2.py
odoo/addons/printer_zpl2/tests/test_test_mode.py
odoo/addons/printer_zpl2/tests/test_wizard_import_zpl2.py
odoo/addons/printer_zpl2/tests/test_wizard_print_record_label.py
odoo/addons/printer_zpl2/views/printing_label_zpl2.xml
odoo14_addon_printer_zpl2-14.0.2.1.1.dist-info/METADATA
odoo14_addon_printer_zpl2-14.0.2.1.1.dist-info/WHEEL
odoo14_addon_printer_zpl2-14.0.2.1.1.dist-info/top_level.txt
odoo14_addon_printer_zpl2-14.0.2.1.1.dist-info/RECORD
