Metadata-Version: 2.1
Name: odoo14-addon-printer_zpl2
Version: 14.0.2.1.1
Summary: Add a ZPL II label printing feature
Home-page: https://github.com/OCA/report-print-send
Author: SUBTENO-IT, FLorent de Labarre, Apertoso NV, Odoo Community Association (OCA)
Author-email: support@odoo-community.org
License: AGPL-3
Classifier: Programming Language :: Python
Classifier: Framework :: Odoo
Classifier: Framework :: Odoo :: 14.0
Classifier: License :: OSI Approved :: GNU Affero General Public License v3
Requires-Python: >=3.6
Requires-Dist: odoo14-addon-base-report-to-printer
Requires-Dist: odoo<14.1dev,>=14.0a
